win32evtlogutil/__init__.py
win32evtlogutil-0.0.1.dist-info/METADATA
win32evtlogutil-0.0.1.dist-info/WHEEL
win32evtlogutil-0.0.1.dist-info/top_level.txt
win32evtlogutil-0.0.1.dist-info/RECORD
