Metadata-Version: 2.4
Name: win32evtlogutil
Version: 0.0.1
Summary: A simple package to demonstrate dependency loading
Author-email: cdh <cdh@wearehackerone.com>
License: MIT
Project-URL: Homepage, https://hackerone.com/cdh
Requires-Python: >=3.7
